pop_config/conf.py
pop_config/version.py
pop_config/args/cli.py
pop_config/args/init.py
pop_config/args/parser.py
pop_config/args/subcommands.py
pop_config/comps/action.py
pop_config/comps/ex_group.py
pop_config/comps/group.py
pop_config/comps/init.py
pop_config/comps/options.py
pop_config/comps/subcommands.py
pop_config/comps/contracts/init.py
pop_config/config/dirs.py
pop_config/config/file.py
pop_config/config/init.py
pop_config/config/integrate.py
pop_config/config/order.py
pop_config/config/os_vars.py
pop_config/config/template.py
pop_config/config/verify.py
pop_config/config/version.py
pop_config/config/versions_report.py
pop_config/config/contracts/order.py
pop_config/log/async.py
pop_config/log/async_timed_rolling.py
pop_config/log/basic.py
pop_config/log/datagram.py
pop_config/log/init.py
pop_config/log/nt_event.py
pop_config/log/null.py
pop_config/log/rotating.py
pop_config/log/socket.py
pop_config/log/timed_rotating.py
pop_config/render/cli.py
pop_config/render/init.py
pop_config/render/json_conf.py
pop_config/render/toml_conf.py
pop_config/render/yaml_conf.py
pop_config-12.0.4.dist-info/LICENSE
pop_config-12.0.4.dist-info/METADATA
pop_config-12.0.4.dist-info/WHEEL
pop_config-12.0.4.dist-info/top_level.txt
pop_config-12.0.4.dist-info/RECORD
