Metadata-Version: 2.1
Name: pop-config
Version: 12.0.4
Summary: The official tool to allow for creating and app-merging configuration options for pop projects.
Home-page: https://vmware.gitlab.io/pop/pop-config/en/latest/index.html
Author: VMware, Inc.
Author-email: idemproject@vmware.com
License: Apache Software License 2.0
Project-URL: Code, https://gitlab.com/vmware/pop/pop-config
Project-URL: Issue tracker, https://gitlab.com/vmware/pop/pop-config/issues
Classifier: Environment :: Console
Classifier: Intended Audience :: Developers
Classifier: Intended Audience :: Information Technology
Classifier: Intended Audience :: System Administrators
Classifier: Operating System :: OS Independent
Classifier: Programming Language :: Python
Classifier: Programming Language :: Python :: 3.8
Classifier: Programming Language :: Python :: 3.9
Classifier: Programming Language :: Python :: 3.10
Classifier: Programming Language :: Python :: 3.11
Classifier: Development Status :: 5 - Production/Stable
Classifier: License :: OSI Approved :: Apache Software License
Requires-Python: >=3.8
Provides-Extra: full
Provides-Extra: nt
Provides-Extra: async
License-File: LICENSE
